pwd_hasher/__init__.py
pwd_hasher/hasher.py
password_hasher-0.1.dist-info/METADATA
password_hasher-0.1.dist-info/WHEEL
password_hasher-0.1.dist-info/top_level.txt
password_hasher-0.1.dist-info/RECORD
