Metadata-Version: 2.1
Name: password_hasher
Version: 0.1
Summary: A package for hashing and salting passwords.
Author: Katsurameen
Author-email: almawahib083@gmail.com
Requires-Dist: bcrypt
